nonebot_plugin_eavesdropper/__init__.py
nonebot_plugin_eavesdropper/utils.py
nonebot_plugin_eavesdropper-0.0.11.dist-info/LICENSE
nonebot_plugin_eavesdropper-0.0.11.dist-info/METADATA
nonebot_plugin_eavesdropper-0.0.11.dist-info/WHEEL
nonebot_plugin_eavesdropper-0.0.11.dist-info/RECORD
