Metadata-Version: 2.1
Name: nonebot-plugin-eavesdropper
Version: 0.0.11
Summary: Eavesdropper in NoneBot2
Home-page: https://github.com/tkgs0/nonebot-plugin-eavesdropper
License: MIT
Keywords: nonebot,eavesdropper
Author: 月ヶ瀬
Requires-Python: >=3.9,<4.0
Classifier: License :: OSI Approved :: MIT License
Classifier: Programming Language :: Python :: 3
Classifier: Programming Language :: Python :: 3.9
Classifier: Programming Language :: Python :: 3.10
Classifier: Programming Language :: Python :: 3.11
Classifier: Programming Language :: Python :: 3.12
Requires-Dist: nonebot-adapter-onebot (>=2.4.1,<3.0.0)
Requires-Dist: nonebot2 (>=2.3.1,<3.0.0)
Requires-Dist: ujson (>=5.2.0)
Project-URL: Repository, https://github.com/tkgs0/nonebot-plugin-eavesdropper
